Metadata-Version: 1.1
Name: spygame
Version: 0.1a9
Summary: 2D game engine based on pygame and level-tmx files (soon to be: fully openAI gym integrated)
Home-page: http://www.github.com/sven1977/spygame
Author: Sven Mika
Author-email: sven.mika@ducandu.com
License: MIT
Download-URL: https://github.com/sven1977/spygame/archive/spygame-0.1.zip
Keywords: python-3,pygame,2d-game-engine,tmx-files,game-engine-library,reinforcement-learning,openai-gym,openai-rllab,game-engine,the-lost-vikings,lost-viking-game
Platform: UNKNOWN
